PathPandem/__init__.py
PathPandem/__main__.py
PathPandem/cli.py
PathPandem/compose_pop.py
PathPandem/db-gen-irwin_hall.py
PathPandem/definitions.py
PathPandem/misc.py
PathPandem/pathogen.py
PathPandem/person.py
PathPandem/plot.py
PathPandem/population.py
PathPandem/reverse_cfr_database.pkl
PathPandem/simul.py
PathPandem/spread_simul.py
PathPandem-1.0.2.4.data/scripts/PathPandem
PathPandem-1.0.2.4.data/scripts/spread_simul.py
PathPandem-1.0.2.4.dist-info/LICENSE
PathPandem-1.0.2.4.dist-info/METADATA
PathPandem-1.0.2.4.dist-info/WHEEL
PathPandem-1.0.2.4.dist-info/top_level.txt
PathPandem-1.0.2.4.dist-info/RECORD
