Metadata-Version: 2.1
Name: PathPandem
Version: 1.0.2.4
Summary: Simulate Pandemic Pathogen Outbreak
Home-page: UNKNOWN
Author: Pradyumna Paranjape
Author-email: pradyparanjpe@rediffmail.com
License: GPLv3
Platform: UNKNOWN
Requires-Dist: numpy
Requires-Dist: gooey
Requires-Dist: matplotlib
